brillouin_zone.cpython-35m-darwin.so
brillouin_zone-1.1.5.dist-info/DESCRIPTION.rst
brillouin_zone-1.1.5.dist-info/METADATA
brillouin_zone-1.1.5.dist-info/RECORD
brillouin_zone-1.1.5.dist-info/WHEEL
brillouin_zone-1.1.5.dist-info/metadata.json
brillouin_zone-1.1.5.dist-info/top_level.txt
