Metadata-Version: 2.0
Name: brillouin-zone
Version: 1.1.5
Summary: Provides the object bz, that defines a lattice in mometum space.
Home-page: UNKNOWN
Author: Marie-Therese Philipp
Author-email: marie.therese1@gmx.de
License: MIT
Keywords: condensed matter,many-body physics,TU Wien,Russian Quantum Center
Platform: UNKNOWN
Classifier: Development Status :: 3 - Alpha
Classifier: Intended Audience :: Science/Research
Classifier: Topic :: Scientific/Engineering :: Physics
Classifier: Programming Language :: C++
Classifier: Programming Language :: Python :: 3.5
Classifier: Operating System :: MacOS
